gbdx_surface_water-0.0.12.dist-info/METADATA
gbdx_surface_water-0.0.12.dist-info/RECORD
gbdx_surface_water-0.0.12.dist-info/WHEEL
gbdx_surface_water-0.0.12.dist-info/top_level.txt
gbdxwater/__init__.py
gbdxwater/algorithms.py
gbdxwater/widgets.py
water/__init__.py
water/algorithms.py
water/plots.py
water/widgets.py
