Metadata-Version: 2.1
Name: gbdx-surface-water
Version: 0.0.12
Summary: Functions and constants used by the surface water detection via GBDX Notebook
Home-page: UNKNOWN
Author: Gennadii Donchyts
Author-email: gennadiy.donchyts@gmail.com
License: UNKNOWN
Requires-Dist: shapely
Requires-Dist: opencv-python
Requires-Dist: earthengine-api
Requires-Dist: oauth2client
Requires-Dist: shapely
Requires-Dist: gbdxtools
Requires-Dist: numpy
Requires-Dist: matplotlib
Requires-Dist: scikit-image
Requires-Dist: pandas
Requires-Dist: rasterio
